osbot_jira/Deploy.py
osbot_jira/Jira.py
osbot_jira/__init__.py
osbot_jira/api/API_Issues.py
osbot_jira/api/GS_Bot_Jira.py
osbot_jira/api/GS_Bot_Jira_Commands.py
osbot_jira/api/NGrok_Jira.py
osbot_jira/api/__init__.py
osbot_jira/api/elk/Elk_To_Slack.py
osbot_jira/api/elk/__init__.py
osbot_jira/api/graph/Filters.py
osbot_jira/api/graph/GS_Graph.py
osbot_jira/api/graph/GS_Graph_Puml.py
osbot_jira/api/graph/Graph_View.py
osbot_jira/api/graph/Lambda_Graph.py
osbot_jira/api/graph/Lambda_Graph_Commands.py
osbot_jira/api/graph/__init__.py
osbot_jira/api/graph/Graph_Commands/Commands_Helper.py
osbot_jira/api/graph/Graph_Commands/Graph_Filters.py
osbot_jira/api/graph/Graph_Commands/Nodes.py
osbot_jira/api/graph/Graph_Commands/Vis_JS.py
osbot_jira/api/graph/Graph_Commands/__init__.py
osbot_jira/api/jira_server/API_Jira.py
osbot_jira/api/jira_server/API_Jira_Rest.py
osbot_jira/api/jira_server/Jira_Commands.py
osbot_jira/api/jira_server/__init__.py
osbot_jira/lambdas/__init__.py
osbot_jira/lambdas/elastic_jira.py
osbot_jira/lambdas/elk_to_slack.py
osbot_jira/lambdas/graph.py
osbot_jira/lambdas/jira.py
osbot_jira-0.4.4.dist-info/LICENSE
osbot_jira-0.4.4.dist-info/METADATA
osbot_jira-0.4.4.dist-info/WHEEL
osbot_jira-0.4.4.dist-info/top_level.txt
osbot_jira-0.4.4.dist-info/RECORD
