Metadata-Version: 2.1
Name: osbot-jira
Version: 0.4.4
Summary: OWASP Security Bot - Jira
Home-page: https://github.com/pbx-gs/OSBot-Jira
Author: Dinis Cruz
Author-email: dinis.cruz@owasp.org
License: UNKNOWN
Platform: UNKNOWN
Classifier: Programming Language :: Python :: 3
Classifier: License :: OSI Approved :: MIT License
Classifier: Operating System :: OS Independent
